pyAIC/__init__.py
pyAIC-0.0.6.dist-info/LICENSE.txt
pyAIC-0.0.6.dist-info/METADATA
pyAIC-0.0.6.dist-info/WHEEL
pyAIC-0.0.6.dist-info/top_level.txt
pyAIC-0.0.6.dist-info/RECORD
