Metadata-Version: 2.1
Name: pyAIC
Version: 0.0.6
Summary: A package to manipulate, convert and validate AIC codes
Home-page: https://github.com/FabrizioMontanari/pyAIC
Author: FabrizioMontanari
Author-email: 
License: UNKNOWN
Platform: UNKNOWN
Classifier: Programming Language :: Python :: 2
Classifier: Programming Language :: Python :: 3
Classifier: License :: OSI Approved :: MIT License
Classifier: Operating System :: OS Independent
Requires-Python: >=2.7
